{
    "type": "FeatureCollection",
    "features": [
        {
            "type": "Feature",
            "id": "boundary",
            "geometry": {
                "type": "Polygon",
                "coordinates": [
                    [
                        [
                            0.0,
                            0.0
                        ],
                        [
                            100.0,
                            0.0
                        ],
                        [
                            100.0,
                            100.0
                        ],
                        [
                            0.0,
                            100.0
                        ],
                        [
                            0.0,
                            0.0
                        ]
                    ]
                ]
            },
            "properties": {}
        },
        {
            "type": "Feature",
            "id": "tasks",
            "geometry": {
                "type": "MultiLineString",
                "coordinates": [
                    [
                        [
                            39.8787,
                            49.479
                        ],
                        [
                            45.0289,
                            47.878
                        ]
                    ],
                    [
                        [
                            29.5785,
                            42.675
                        ],
                        [
                            33.5699,
                            44.6637
                        ]
                    ],
                    [
                        [
                            0.0,
                            40.5
                        ],
                        [
                            27.636861,
                            40.5
                        ]
                    ],
                    [
                        [
                            31.234308,
                            43.5
                        ],
                        [
                            0.0,
                            43.5
                        ]
                    ],
                    [
                        [
                            100.0,
                            43.5
                        ],
                        [
                            34.643615,
                            43.5
                        ]
                    ],
                    [
                        [
                            0.0,
                            46.5
                        ],
                        [
                            100.0,
                            46.5
                        ]
                    ],
                    [
                        [
                            9.97767,
                            49.5
                        ],
                        [
                            0.0,
                            49.5
                        ]
                    ],
                    [
                        [
                            19.7559,
                            50.946
                        ],
                        [
                            7.88736,
                            54.4142
                        ]
                    ],
                    [
                        [
                            39.881486,
                            49.5
                        ],
                        [
                            19.112711,
                            49.5
                        ]
                    ],
                    [
                        [
                            35.9289,
                            52.2614
                        ],
                        [
                            40.091,
                            51.0794
                        ]
                    ],
                    [
                        [
                            14.437951,
                            52.5
                        ],
                        [
                            35.987308,
                            52.5
                        ]
                    ],
                    [
                        [
                            6.87352,
                            50.2643
                        ],
                        [
                            18.211,
                            47.4728
                        ]
                    ],
                    [
                        [
                            0.0,
                            52.5
                        ],
                        [
                            7.419712,
                            52.5
                        ]
                    ],
                    [
                        [
                            36.721685,
                            55.5
                        ],
                        [
                            0.0,
                            55.5
                        ]
                    ],
                    [
                        [
                            46.6489,
                            55.4101
                        ],
                        [
                            37.4414,
                            58.4401
                        ]
                    ],
                    [
                        [
                            78.629001,
                            55.5
                        ],
                        [
                            46.375714,
                            55.5
                        ]
                    ],
                    [
                        [
                            46.022997,
                            52.5
                        ],
                        [
                            79.361467,
                            52.5
                        ]
                    ],
                    [
                        [
                            100.0,
                            49.5
                        ],
                        [
                            45.377759,
                            49.5
                        ]
                    ],
                    [
                        [
                            60.6736,
                            64.5
                        ],
                        [
                            100.0,
                            64.5
                        ]
                    ],
                    [
                        [
                            100.0,
                            67.5
                        ],
                        [
                            59.015169,
                            67.5
                        ]
                    ],
                    [
                        [
                            57.356739,
                            70.5
                        ],
                        [
                            100.0,
                            70.5
                        ]
                    ],
                    [
                        [
                            72.754742,
                            79.5
                        ],
                        [
                            52.381447,
                            79.5
                        ]
                    ],
                    [
                        [
                            79.4107,
                            75.3097
                        ],
                        [
                            72.7443,
                            79.4784
                        ]
                    ],
                    [
                        [
                            54.039878,
                            76.5
                        ],
                        [
                            77.507225,
                            76.5
                        ]
                    ],
                    [
                        [
                            100.0,
                            73.5
                        ],
                        [
                            55.698308,
                            73.5
                        ]
                    ],
                    [
                        [
                            80.05973,
                            76.5
                        ],
                        [
                            100.0,
                            76.5
                        ]
                    ],
                    [
                        [
                            100.0,
                            79.5
                        ],
                        [
                            81.695529,
                            79.5
                        ]
                    ],
                    [
                        [
                            83.331328,
                            82.5
                        ],
                        [
                            100.0,
                            82.5
                        ]
                    ],
                    [
                        [
                            76.4537,
                            87.1514
                        ],
                        [
                            83.6478,
                            83.0804
                        ]
                    ],
                    [
                        [
                            100.0,
                            85.5
                        ],
                        [
                            79.371985,
                            85.5
                        ]
                    ],
                    [
                        [
                            0.0,
                            91.5
                        ],
                        [
                            100.0,
                            91.5
                        ]
                    ],
                    [
                        [
                            100.0,
                            94.5
                        ],
                        [
                            0.0,
                            94.5
                        ]
                    ],
                    [
                        [
                            0.0,
                            97.5
                        ],
                        [
                            100.0,
                            97.5
                        ]
                    ],
                    [
                        [
                            100.0,
                            100.0
                        ],
                        [
                            0.0,
                            100.0
                        ]
                    ],
                    [
                        [
                            11.811346,
                            88.5
                        ],
                        [
                            100.0,
                            88.5
                        ]
                    ],
                    [
                        [
                            6.96578,
                            89.3268
                        ],
                        [
                            14.2816,
                            88.0785
                        ]
                    ],
                    [
                        [
                            0.0,
                            89.3268
                        ],
                        [
                            6.96578,
                            89.3268
                        ]
                    ],
                    [
                        [
                            0.0,
                            81.2131
                        ],
                        [
                            0.0,
                            89.3268
                        ]
                    ],
                    [
                        [
                            3.4324,
                            81.2131
                        ],
                        [
                            0.0,
                            81.2131
                        ]
                    ],
                    [
                        [
                            3.992823,
                            82.5
                        ],
                        [
                            4.463058,
                            82.5
                        ]
                    ],
                    [
                        [
                            12.3662,
                            81.2131
                        ],
                        [
                            4.02396,
                            82.5715
                        ]
                    ],
                    [
                        [
                            45.493307,
                            82.5
                        ],
                        [
                            12.725236,
                            82.5
                        ]
                    ],
                    [
                        [
                            49.5138,
                            84.6874
                        ],
                        [
                            41.9178,
                            80.5547
                        ]
                    ],
                    [
                        [
                            74.205048,
                            82.5
                        ],
                        [
                            50.723017,
                            82.5
                        ]
                    ],
                    [
                        [
                            13.562216,
                            85.5
                        ],
                        [
                            75.655355,
                            85.5
                        ]
                    ],
                    [
                        [
                            0.0,
                            70.5
                        ],
                        [
                            12.222018,
                            70.5
                        ]
                    ],
                    [
                        [
                            21.308628,
                            73.5
                        ],
                        [
                            0.0,
                            73.5
                        ]
                    ],
                    [
                        [
                            0.0,
                            76.5
                        ],
                        [
                            30.395238,
                            76.5
                        ]
                    ],
                    [
                        [
                            2.05759,
                            89.3268
                        ],
                        [
                            0.0,
                            84.601956
                        ]
                    ],
                    [
                        [
                            1.796336,
                            81.2131
                        ],
                        [
                            5.329717,
                            89.3268
                        ]
                    ],
                    [
                        [
                            42.495325,
                            79.5
                        ],
                        [
                            0.0,
                            79.5
                        ]
                    ],
                    [
                        [
                            52.773458,
                            57.6065
                        ],
                        [
                            42.026518,
                            77.233
                        ]
                    ],
                    [
                        [
                            38.606207,
                            77.233
                        ],
                        [
                            49.353148,
                            57.6065
                        ]
                    ],
                    [
                        [
                            43.261586,
                            62.484848
                        ],
                        [
                            35.185896,
                            77.233
                        ]
                    ],
                    [
                        [
                            32.6154,
                            77.233
                        ],
                        [
                            43.736673,
                            77.233
                        ]
                    ],
                    [
                        [
                            38.596298,
                            64.758475
                        ],
                        [
                            33.705771,
                            73.689755
                        ]
                    ],
                    [
                        [
                            46.2386,
                            61.034
                        ],
                        [
                            37.7367,
                            65.1774
                        ]
                    ],
                    [
                        [
                            45.932837,
                            57.6065
                        ],
                        [
                            45.175929,
                            58.988796
                        ]
                    ],
                    [
                        [
                            16.088568,
                            58.5
                        ],
                        [
                            42.544229,
                            58.5
                        ]
                    ],
                    [
                        [
                            36.11959,
                            61.5
                        ],
                        [
                            25.614223,
                            61.5
                        ]
                    ],
                    [
                        [
                            36.950029,
                            63.497456
                        ],
                        [
                            30.735315,
                            61.5402
                        ]
                    ],
                    [
                        [
                            32.6154,
                            77.233
                        ],
                        [
                            36.4106,
                            64.9002
                        ]
                    ],
                    [
                        [
                            7.76655,
                            69.029
                        ],
                        [
                            32.6154,
                            77.233
                        ]
                    ],
                    [
                        [
                            0.0,
                            67.5
                        ],
                        [
                            8.808005,
                            67.5
                        ]
                    ],
                    [
                        [
                            10.851409,
                            64.5
                        ],
                        [
                            0.0,
                            64.5
                        ]
                    ],
                    [
                        [
                            0.0,
                            61.5
                        ],
                        [
                            12.894813,
                            61.5
                        ]
                    ],
                    [
                        [
                            14.938218,
                            58.5
                        ],
                        [
                            0.0,
                            58.5
                        ]
                    ],
                    [
                        [
                            25.741866,
                            61.5402
                        ],
                        [
                            15.1414,
                            58.2017
                        ]
                    ],
                    [
                        [
                            36.0335,
                            61.5402
                        ],
                        [
                            25.741866,
                            61.5402
                        ]
                    ],
                    [
                        [
                            44.4577,
                            57.6065
                        ],
                        [
                            36.0335,
                            61.5402
                        ]
                    ],
                    [
                        [
                            54.483614,
                            57.6065
                        ],
                        [
                            44.4577,
                            57.6065
                        ]
                    ],
                    [
                        [
                            55.2414,
                            56.2226
                        ],
                        [
                            54.483614,
                            57.6065
                        ]
                    ],
                    [
                        [
                            62.8169,
                            60.6229
                        ],
                        [
                            55.2414,
                            56.2226
                        ]
                    ],
                    [
                        [
                            100.0,
                            61.5
                        ],
                        [
                            62.33203,
                            61.5
                        ]
                    ],
                    [
                        [
                            83.31249,
                            58.5
                        ],
                        [
                            100.0,
                            58.5
                        ]
                    ],
                    [
                        [
                            100.0,
                            55.5
                        ],
                        [
                            86.105402,
                            55.5
                        ]
                    ],
                    [
                        [
                            84.324241,
                            52.5
                        ],
                        [
                            100.0,
                            52.5
                        ]
                    ],
                    [
                        [
                            77.2011,
                            54.2575
                        ],
                        [
                            82.1496,
                            50.2318
                        ]
                    ],
                    [
                        [
                            82.7594,
                            59.0941
                        ],
                        [
                            77.2011,
                            54.2575
                        ]
                    ],
                    [
                        [
                            59.162143,
                            58.5
                        ],
                        [
                            82.076651,
                            58.5
                        ]
                    ],
                    [
                        [
                            100.0,
                            28.5
                        ],
                        [
                            45.14673,
                            28.5
                        ]
                    ],
                    [
                        [
                            44.970573,
                            25.5
                        ],
                        [
                            100.0,
                            25.5
                        ]
                    ],
                    [
                        [
                            43.0734,
                            25.9457
                        ],
                        [
                            44.962,
                            25.354
                        ]
                    ],
                    [
                        [
                            0.0,
                            25.5
                        ],
                        [
                            44.495994,
                            25.5
                        ]
                    ],
                    [
                        [
                            100.0,
                            22.5
                        ],
                        [
                            0.0,
                            22.5
                        ]
                    ],
                    [
                        [
                            32.78013,
                            19.5
                        ],
                        [
                            100.0,
                            19.5
                        ]
                    ],
                    [
                        [
                            68.223782,
                            16.5
                        ],
                        [
                            36.670649,
                            16.5
                        ]
                    ],
                    [
                        [
                            100.0,
                            13.5
                        ],
                        [
                            71.61695,
                            13.5
                        ]
                    ],
                    [
                        [
                            70.220116,
                            16.5
                        ],
                        [
                            100.0,
                            16.5
                        ]
                    ],
                    [
                        [
                            62.2155,
                            13.7394
                        ],
                        [
                            69.8683,
                            17.2556
                        ]
                    ],
                    [
                        [
                            36.954843,
                            10.5
                        ],
                        [
                            58.820766,
                            10.5
                        ]
                    ],
                    [
                        [
                            43.0096,
                            11.612
                        ],
                        [
                            33.3827,
                            9.84395
                        ]
                    ],
                    [
                        [
                            31.6026,
                            20.408
                        ],
                        [
                            43.0096,
                            11.612
                        ]
                    ],
                    [
                        [
                            0.0,
                            19.5
                        ],
                        [
                            31.755603,
                            19.5
                        ]
                    ],
                    [
                        [
                            32.261119,
                            16.5
                        ],
                        [
                            0.0,
                            16.5
                        ]
                    ],
                    [
                        [
                            32.766636,
                            13.5
                        ],
                        [
                            0.0,
                            13.5
                        ]
                    ],
                    [
                        [
                            0.0,
                            10.5
                        ],
                        [
                            33.272152,
                            10.5
                        ]
                    ],
                    [
                        [
                            52.341754,
                            7.5
                        ],
                        [
                            0.0,
                            7.5
                        ]
                    ],
                    [
                        [
                            56.7384,
                            4.13669
                        ],
                        [
                            52.0348,
                            7.35787
                        ]
                    ],
                    [
                        [
                            72.3447,
                            11.937
                        ],
                        [
                            56.7384,
                            4.13669
                        ]
                    ],
                    [
                        [
                            100.0,
                            10.5
                        ],
                        [
                            69.469654,
                            10.5
                        ]
                    ],
                    [
                        [
                            63.467469,
                            7.5
                        ],
                        [
                            100.0,
                            7.5
                        ]
                    ],
                    [
                        [
                            100.0,
                            4.5
                        ],
                        [
                            57.465285,
                            4.5
                        ]
                    ],
                    [
                        [
                            0.0,
                            1.5
                        ],
                        [
                            100.0,
                            1.5
                        ]
                    ],
                    [
                        [
                            56.207891,
                            4.5
                        ],
                        [
                            0.0,
                            4.5
                        ]
                    ],
                    [
                        [
                            63.0088,
                            12.4392
                        ],
                        [
                            52.0348,
                            7.35787
                        ]
                    ],
                    [
                        [
                            40.561167,
                            13.5
                        ],
                        [
                            62.361567,
                            13.5
                        ]
                    ],
                    [
                        [
                            100.0,
                            37.5
                        ],
                        [
                            29.094419,
                            37.5
                        ]
                    ],
                    [
                        [
                            35.182215,
                            40.5
                        ],
                        [
                            100.0,
                            40.5
                        ]
                    ],
                    [
                        [
                            28.7117,
                            37.3114
                        ],
                        [
                            35.3129,
                            40.5644
                        ]
                    ],
                    [
                        [
                            0.0,
                            37.5
                        ],
                        [
                            28.621069,
                            37.5
                        ]
                    ],
                    [
                        [
                            100.0,
                            34.5
                        ],
                        [
                            0.0,
                            34.5
                        ]
                    ],
                    [
                        [
                            0.0,
                            31.5
                        ],
                        [
                            100.0,
                            31.5
                        ]
                    ],
                    [
                        [
                            43.827755,
                            28.5
                        ],
                        [
                            0.0,
                            28.5
                        ]
                    ]
                ]
            },
            "properties": {}
        },
        {
            "type": "Feature",
            "id": "obstacles",
            "geometry": {
                "type": "MultiPolygon",
                "coordinates": [
                    [
                        [
                            [
                                14.2816,
                                88.0785
                            ],
                            [
                                12.3662,
                                81.2131
                            ],
                            [
                                4.02396,
                                82.5715
                            ],
                            [
                                6.96578,
                                89.3268
                            ],
                            [
                                14.2816,
                                88.0785
                            ]
                        ]
                    ],
                    [
                        [
                            [
                                19.7559,
                                50.946
                            ],
                            [
                                18.211,
                                47.4728
                            ],
                            [
                                6.87352,
                                50.2643
                            ],
                            [
                                7.88736,
                                54.4142
                            ],
                            [
                                19.7559,
                                50.946
                            ]
                        ]
                    ],
                    [
                        [
                            [
                                36.4106,
                                64.9002
                            ],
                            [
                                15.1414,
                                58.2017
                            ],
                            [
                                7.76655,
                                69.029
                            ],
                            [
                                32.6154,
                                77.233
                            ],
                            [
                                36.4106,
                                64.9002
                            ]
                        ]
                    ],
                    [
                        [
                            [
                                35.3129,
                                40.5644
                            ],
                            [
                                28.7117,
                                37.3114
                            ],
                            [
                                27.3395,
                                40.1669
                            ],
                            [
                                29.5785,
                                42.675
                            ],
                            [
                                33.5699,
                                44.6637
                            ],
                            [
                                34.8013,
                                43.3291
                            ],
                            [
                                35.3129,
                                40.5644
                            ]
                        ]
                    ],
                    [
                        [
                            [
                                43.0096,
                                11.612
                            ],
                            [
                                33.3827,
                                9.84395
                            ],
                            [
                                31.6026,
                                20.408
                            ],
                            [
                                43.0096,
                                11.612
                            ]
                        ]
                    ],
                    [
                        [
                            [
                                46.6489,
                                55.4101
                            ],
                            [
                                45.0289,
                                47.878
                            ],
                            [
                                39.8787,
                                49.479
                            ],
                            [
                                40.091,
                                51.0794
                            ],
                            [
                                35.9289,
                                52.2614
                            ],
                            [
                                37.4414,
                                58.4401
                            ],
                            [
                                46.6489,
                                55.4101
                            ]
                        ]
                    ],
                    [
                        [
                            [
                                45.2926,
                                30.9842
                            ],
                            [
                                44.962,
                                25.354
                            ],
                            [
                                43.0734,
                                25.9457
                            ],
                            [
                                44.5739,
                                31.0265
                            ],
                            [
                                45.2926,
                                30.9842
                            ]
                        ]
                    ],
                    [
                        [
                            [
                                46.2386,
                                61.034
                            ],
                            [
                                44.4577,
                                57.6065
                            ],
                            [
                                36.0335,
                                61.5402
                            ],
                            [
                                37.7367,
                                65.1774
                            ],
                            [
                                46.2386,
                                61.034
                            ]
                        ]
                    ],
                    [
                        [
                            [
                                62.8169,
                                60.6229
                            ],
                            [
                                55.2414,
                                56.2226
                            ],
                            [
                                41.9178,
                                80.5547
                            ],
                            [
                                49.5138,
                                84.6874
                            ],
                            [
                                62.8169,
                                60.6229
                            ]
                        ]
                    ],
                    [
                        [
                            [
                                72.3447,
                                11.937
                            ],
                            [
                                56.7384,
                                4.13669
                            ],
                            [
                                52.0348,
                                7.35787
                            ],
                            [
                                63.0088,
                                12.4392
                            ],
                            [
                                62.2155,
                                13.7394
                            ],
                            [
                                69.8683,
                                17.2556
                            ],
                            [
                                72.3447,
                                11.937
                            ]
                        ]
                    ],
                    [
                        [
                            [
                                83.6478,
                                83.0804
                            ],
                            [
                                79.4107,
                                75.3097
                            ],
                            [
                                72.7443,
                                79.4784
                            ],
                            [
                                76.4537,
                                87.1514
                            ],
                            [
                                83.6478,
                                83.0804
                            ]
                        ]
                    ],
                    [
                        [
                            [
                                86.6449,
                                54.9205
                            ],
                            [
                                82.1496,
                                50.2318
                            ],
                            [
                                77.2011,
                                54.2575
                            ],
                            [
                                82.7594,
                                59.0941
                            ],
                            [
                                86.6449,
                                54.9205
                            ]
                        ]
                    ]
                ]
            },
            "properties": {}
        }
    ]
}